README.rst
setup.py
sphinxcontrib/__init__.py
sphinxcontrib/versioning/__init__.py
sphinxcontrib/versioning/__main__.py
sphinxcontrib/versioning/git.py
sphinxcontrib/versioning/lib.py
sphinxcontrib/versioning/routines.py
sphinxcontrib/versioning/setup_logging.py
sphinxcontrib/versioning/sphinx_.py
sphinxcontrib/versioning/versions.py
sphinxcontrib/versioning/_static/banner.css
sphinxcontrib/versioning/_templates/banner.html
sphinxcontrib/versioning/_templates/versions.html
sphinxcontrib_versioning.egg-info/PKG-INFO
sphinxcontrib_versioning.egg-info/SOURCES.txt
sphinxcontrib_versioning.egg-info/dependency_links.txt
sphinxcontrib_versioning.egg-info/entry_points.txt
sphinxcontrib_versioning.egg-info/not-zip-safe
sphinxcontrib_versioning.egg-info/requires.txt
sphinxcontrib_versioning.egg-info/top_level.txt