Metadata-Version: 1.1
Name: sphinxcontrib-versioning
Version: 2.2.1
Summary: Sphinx extension that allows building versioned docs for self-hosting.
Home-page: https://github.com/Robpol86/sphinxcontrib-versioning
Author: @Robpol86
Author-email: robpol86@gmail.com
License: MIT
Keywords: sphinx versioning versions version branches tags
Platform: UNKNOWN
Classifier: Development Status :: 5 - Production/Stable
Classifier: Environment :: Console
Classifier: Framework :: Sphinx :: Extension
Classifier: Intended Audience :: Developers
Classifier: License :: OSI Approved :: MIT License
Classifier: Operating System :: MacOS
Classifier: Operating System :: POSIX :: Linux
Classifier: Operating System :: POSIX
Classifier: Programming Language :: Python :: 2.7
Classifier: Programming Language :: Python :: 3.3
Classifier: Programming Language :: Python :: 3.4
Classifier: Programming Language :: Python :: 3.5
Classifier: Programming Language :: Python :: Implementation :: PyPy
Classifier: Topic :: Documentation :: Sphinx
Classifier: Topic :: Software Development :: Documentation
